inetbox/__init__.py
inetbox/conversions.py
inetbox/inetbox.py
inetbox/lin.py
inetbox/tools.py
inetbox/translations.py
inetbox/truma_service.py
inetbox_py-0.4.dist-info/METADATA
inetbox_py-0.4.dist-info/WHEEL
inetbox_py-0.4.dist-info/licenses/LICENSE
inetbox_py-0.4.dist-info/RECORD
