Metadata-Version: 2.4
Name: inetbox-py
Version: 0.4
Summary: 
License-File: LICENSE
Author: Daniel Fett
Author-email: fett@danielfett.de
Requires-Python: >=3.7,<4.0
Classifier: Programming Language :: Python :: 3
Classifier: Programming Language :: Python :: 3.7
Classifier: Programming Language :: Python :: 3.8
Classifier: Programming Language :: Python :: 3.9
Classifier: Programming Language :: Python :: 3.10
Classifier: Programming Language :: Python :: 3.11
Classifier: Programming Language :: Python :: 3.12
Classifier: Programming Language :: Python :: 3.13
Classifier: Programming Language :: Python :: 3.14
Provides-Extra: truma-service
Requires-Dist: bitstruct (>=8.15.1,<9.0.0)
Requires-Dist: miqro (>=1.2.2)
Requires-Dist: paho-mqtt (>=1.6.1,<2.0.0) ; extra == "truma-service"
Requires-Dist: pyserial (>=3.5,<4.0)
Requires-Dist: python-dateutil (>2.8.0)
